rogo/__init__.py
rogo/app.py
rogo/client.py
rogo/database.py
rogo/driver.py
rogo/model.py
rogo/orgtest.py
rogo/runner.py
rogo-0.1.1.dist-info/LICENSE
rogo-0.1.1.dist-info/METADATA
rogo-0.1.1.dist-info/WHEEL
rogo-0.1.1.dist-info/entry_points.txt
rogo-0.1.1.dist-info/top_level.txt
rogo-0.1.1.dist-info/RECORD
