Metadata-Version: 2.1
Name: rogo
Version: 0.1.1
Summary: A tool for test-driven teaching.
Maintainer-email: Michal J Wallace <michal.wallace@gmail.com>
License: MIT License
Project-URL: Homepage, https://tangentcode.com/
Project-URL: Source, https://github.com/tangentstorm/rogo
Project-URL: Live Server, https://rogo.tangentcode.com/
Classifier: License :: OSI Approved :: MIT License
Requires-Python: >=3.11
License-File: LICENSE
Requires-Dist: jwt ~=1.3.1
Requires-Dist: requests ~=2.31.0
Requires-Dist: quart ~=0.19.4
